{"v":"4.8.0","meta":{"g":"LottieFiles AE ","a":"","k":"","d":"","tc":""},"fr":29.9700012207031,"ip":0,"op":61.0000024845809,"w":400,"h":400,"nm":"face-metalinguistica","ddd":0,"assets":[{"id":"comp_0","layers":[{"ddd":0,"ind":1,"ty":1,"nm":"tongue","sr":1,"ks":{"o":{"a":0,"k":100,"ix":11},"r":{"a":0,"k":0,"ix":10},"p":{"a":0,"k":[200,200,0],"ix":2},"a":{"a":0,"k":[200,200,0],"ix":1},"s":{"a":0,"k":[100,100,100],"ix":6}},"ao":0,"hasMask":true,"masksProperties":[{"inv":false,"mode":"a","pt":{"a":0,"k":{"i":[[29.024,0],[0,-18.244],[-29.024,0],[0,18.244]],"o":[[-29.024,0],[0,18.244],[29.024,0],[0,-18.244]],"v":[[200,205.967],[147.447,239],[200,272.033],[252.553,239]],"c":true},"ix":1},"o":{"a":0,"k":100,"ix":3},"x":{"a":0,"k":0,"ix":4},"nm":"Mask 1"}],"sw":400,"sh":400,"sc":"#a04e61","ip":0,"op":600.000024438501,"st":0,"bm":0},{"ddd":0,"ind":2,"ty":1,"nm":"moth","sr":1,"ks":{"o":{"a":0,"k":100,"ix":11},"r":{"a":0,"k":0,"ix":10},"p":{"a":0,"k":[200,200,0],"ix":2},"a":{"a":0,"k":[200,200,0],"ix":1},"s":{"a":0,"k":[100,100,100],"ix":6}},"ao":0,"sw":400,"sh":400,"sc":"#442f01","ip":0,"op":600.000024438501,"st":0,"bm":0}]}],"layers":[{"ddd":0,"ind":1,"ty":4,"nm":"reflext 4","parent":5,"sr":1,"ks":{"o":{"a":0,"k":100,"ix":11},"r":{"a":0,"k":0,"ix":10},"p":{"a":0,"k":[261.932,199.432,0],"ix":2},"a":{"a":0,"k":[-51,-26,0],"ix":1},"s":{"a":0,"k":[97.875,97.875,100],"ix":6}},"ao":0,"shapes":[{"ty":"gr","it":[{"d":1,"ty":"el","s":{"a":0,"k":[57.977,57.977],"ix":2},"p":{"a":0,"k":[0,0],"ix":3},"nm":"Ellipse Path 1","mn":"ADBE Vector Shape - Ellipse","hd":false},{"ty":"gf","o":{"a":0,"k":100,"ix":10},"r":1,"bm":0,"g":{"p":3,"k":{"a":0,"k":[0,1,1,1,0.5,1,1,1,1,1,1,1,0.361,0,0.366,0.5,0.37,1,0.444,0.95,0.518,0.9,0.527,0.45,0.536,0],"ix":9}},"s":{"a":0,"k":[-26.895,-24.652],"ix":5},"e":{"a":1,"k":[{"i":{"x":0.833,"y":0.833},"o":{"x":0.167,"y":0.167},"t":18,"s":[-20.943,-18.569],"to":[25.748,17.386],"ti":[-25.748,-17.386]},{"t":23.0000009368092,"s":[133.545,85.745]}],"ix":6},"t":1,"nm":"Gradient Fill 1","mn":"ADBE Vector Graphic - G-Fill","hd":false},{"ty":"tr","p":{"a":0,"k":[-51.5,-25.5],"ix":2},"a":{"a":0,"k":[0,0],"ix":1},"s":{"a":0,"k":[113.644,116.086],"ix":3},"r":{"a":0,"k":0,"ix":6},"o":{"a":0,"k":100,"ix":7},"sk":{"a":0,"k":0,"ix":4},"sa":{"a":0,"k":0,"ix":5},"nm":"Transform"}],"nm":"Ellipse 2","np":3,"cix":2,"bm":0,"ix":1,"mn":"ADBE Vector Group","hd":false}],"ip":18.000000733155,"op":23.0000009368092,"st":8.00000032584668,"bm":0},{"ddd":0,"ind":2,"ty":4,"nm":"reflext 3","parent":5,"sr":1,"ks":{"o":{"a":0,"k":100,"ix":11},"r":{"a":0,"k":0,"ix":10},"p":{"a":0,"k":[261.932,199.432,0],"ix":2},"a":{"a":0,"k":[-51,-26,0],"ix":1},"s":{"a":0,"k":[97.875,97.875,100],"ix":6}},"ao":0,"shapes":[{"ty":"gr","it":[{"d":1,"ty":"el","s":{"a":0,"k":[57.977,57.977],"ix":2},"p":{"a":0,"k":[0,0],"ix":3},"nm":"Ellipse Path 1","mn":"ADBE Vector Shape - Ellipse","hd":false},{"ty":"gf","o":{"a":0,"k":100,"ix":10},"r":1,"bm":0,"g":{"p":3,"k":{"a":0,"k":[0,1,1,1,0.5,1,1,1,1,1,1,1,0.361,0,0.366,0.5,0.37,1,0.444,0.95,0.518,0.9,0.527,0.45,0.536,0],"ix":9}},"s":{"a":0,"k":[-26.895,-24.652],"ix":5},"e":{"a":1,"k":[{"i":{"x":0.833,"y":0.833},"o":{"x":0.167,"y":0.167},"t":15,"s":[-20.943,-18.569],"to":[25.748,17.386],"ti":[-25.748,-17.386]},{"t":20.0000008146167,"s":[133.545,85.745]}],"ix":6},"t":1,"nm":"Gradient Fill 1","mn":"ADBE Vector Graphic - G-Fill","hd":false},{"ty":"tr","p":{"a":0,"k":[-51.5,-25.5],"ix":2},"a":{"a":0,"k":[0,0],"ix":1},"s":{"a":0,"k":[113.644,116.086],"ix":3},"r":{"a":0,"k":0,"ix":6},"o":{"a":0,"k":100,"ix":7},"sk":{"a":0,"k":0,"ix":4},"sa":{"a":0,"k":0,"ix":5},"nm":"Transform"}],"nm":"Ellipse 2","np":3,"cix":2,"bm":0,"ix":1,"mn":"ADBE Vector Group","hd":false}],"ip":15.0000006109625,"op":20.0000008146167,"st":5.00000020365417,"bm":0},{"ddd":0,"ind":3,"ty":4,"nm":"reflext 2","parent":5,"sr":1,"ks":{"o":{"a":0,"k":100,"ix":11},"r":{"a":0,"k":0,"ix":10},"p":{"a":0,"k":[142.045,199.432,0],"ix":2},"a":{"a":0,"k":[-51,-26,0],"ix":1},"s":{"a":0,"k":[97.875,97.875,100],"ix":6}},"ao":0,"shapes":[{"ty":"gr","it":[{"d":1,"ty":"el","s":{"a":0,"k":[57.977,57.977],"ix":2},"p":{"a":0,"k":[0,0],"ix":3},"nm":"Ellipse Path 1","mn":"ADBE Vector Shape - Ellipse","hd":false},{"ty":"gf","o":{"a":0,"k":100,"ix":10},"r":1,"bm":0,"g":{"p":3,"k":{"a":0,"k":[0,1,1,1,0.5,1,1,1,1,1,1,1,0.361,0,0.366,0.5,0.37,1,0.444,0.95,0.518,0.9,0.527,0.45,0.536,0],"ix":9}},"s":{"a":0,"k":[-26.895,-24.652],"ix":5},"e":{"a":1,"k":[{"i":{"x":0.833,"y":0.833},"o":{"x":0.167,"y":0.167},"t":13,"s":[-20.943,-18.569],"to":[25.748,17.386],"ti":[-25.748,-17.386]},{"t":18.000000733155,"s":[133.545,85.745]}],"ix":6},"t":1,"nm":"Gradient Fill 1","mn":"ADBE Vector Graphic - G-Fill","hd":false},{"ty":"tr","p":{"a":0,"k":[-51.5,-25.5],"ix":2},"a":{"a":0,"k":[0,0],"ix":1},"s":{"a":0,"k":[113.644,116.086],"ix":3},"r":{"a":0,"k":0,"ix":6},"o":{"a":0,"k":100,"ix":7},"sk":{"a":0,"k":0,"ix":4},"sa":{"a":0,"k":0,"ix":5},"nm":"Transform"}],"nm":"Ellipse 2","np":3,"cix":2,"bm":0,"ix":1,"mn":"ADBE Vector Group","hd":false}],"ip":13.0000005295009,"op":18.000000733155,"st":3.00000012219251,"bm":0},{"ddd":0,"ind":4,"ty":4,"nm":"reflext","parent":5,"sr":1,"ks":{"o":{"a":0,"k":100,"ix":11},"r":{"a":0,"k":0,"ix":10},"p":{"a":0,"k":[142.045,199.432,0],"ix":2},"a":{"a":0,"k":[-51,-26,0],"ix":1},"s":{"a":0,"k":[97.875,97.875,100],"ix":6}},"ao":0,"shapes":[{"ty":"gr","it":[{"d":1,"ty":"el","s":{"a":0,"k":[57.977,57.977],"ix":2},"p":{"a":0,"k":[0,0],"ix":3},"nm":"Ellipse Path 1","mn":"ADBE Vector Shape - Ellipse","hd":false},{"ty":"gf","o":{"a":0,"k":100,"ix":10},"r":1,"bm":0,"g":{"p":3,"k":{"a":0,"k":[0,1,1,1,0.5,1,1,1,1,1,1,1,0.361,0,0.366,0.5,0.37,1,0.444,0.95,0.518,0.9,0.527,0.45,0.536,0],"ix":9}},"s":{"a":0,"k":[-26.895,-24.652],"ix":5},"e":{"a":1,"k":[{"i":{"x":0.833,"y":0.833},"o":{"x":0.167,"y":0.167},"t":10,"s":[-20.943,-18.569],"to":[25.748,17.386],"ti":[-25.748,-17.386]},{"t":15.0000006109625,"s":[133.545,85.745]}],"ix":6},"t":1,"nm":"Gradient Fill 1","mn":"ADBE Vector Graphic - G-Fill","hd":false},{"ty":"tr","p":{"a":0,"k":[-51.5,-25.5],"ix":2},"a":{"a":0,"k":[0,0],"ix":1},"s":{"a":0,"k":[113.644,116.086],"ix":3},"r":{"a":0,"k":0,"ix":6},"o":{"a":0,"k":100,"ix":7},"sk":{"a":0,"k":0,"ix":4},"sa":{"a":0,"k":0,"ix":5},"nm":"Transform"}],"nm":"Ellipse 2","np":3,"cix":2,"bm":0,"ix":1,"mn":"ADBE Vector Group","hd":false}],"ip":10.0000004073083,"op":15.0000006109625,"st":0,"bm":0},{"ddd":0,"ind":5,"ty":1,"nm":"glasses","parent":9,"sr":1,"ks":{"o":{"a":0,"k":100,"ix":11},"r":{"a":0,"k":0,"ix":10},"p":{"a":1,"k":[{"i":{"x":0.667,"y":1},"o":{"x":0.333,"y":0},"t":5,"s":[1.301,-65.203,0],"to":[0,9.75,0],"ti":[0,-9.75,0]},{"i":{"x":0.667,"y":0.667},"o":{"x":0.333,"y":0.333},"t":10,"s":[1.301,-6.703,0],"to":[0,0,0],"ti":[0,0,0]},{"i":{"x":0.667,"y":1},"o":{"x":0.333,"y":0},"t":45,"s":[1.301,-6.703,0],"to":[0,-9.75,0],"ti":[0,9.75,0]},{"t":50.0000020365418,"s":[1.301,-65.203,0]}],"ix":2},"a":{"a":0,"k":[200,200,0],"ix":1},"s":{"a":0,"k":[88,88,100],"ix":6}},"ao":0,"hasMask":true,"masksProperties":[{"inv":false,"mode":"f","pt":{"a":1,"k":[{"i":{"x":0.667,"y":1},"o":{"x":0.333,"y":0},"t":5,"s":[{"i":[[3.047,0],[0,0],[24.601,0],[6.991,-17.874],[5.801,0],[4.039,-3.568],[20.321,0],[2.745,-23.878],[0,0],[0,-3.047],[-3.047,0],[0,0],[-24.602,0],[0,26.467],[0.001,0.092],[0,0],[-6.541,0],[0,-6.541],[0,0],[0,-0.092],[-26.467,0],[-2.745,23.878],[0,0],[0,3.047]],"o":[[0,0],[-2.745,-23.878],[-20.321,0],[-4.039,-3.568],[-5.8,0],[-6.991,-17.874],[-24.602,0],[0,0],[-3.047,0],[0,3.047],[0,0],[2.745,23.878],[26.467,0],[0,-0.092],[0,0],[0,-6.541],[6.541,0],[0,0],[-0.001,0.092],[0,26.467],[24.601,0],[0,0],[3.047,0],[0,-3.047]],"v":[[343.182,260.392],[308.922,194.483],[261.241,152],[216.519,182.568],[201.379,176.828],[186.24,182.568],[141.517,152],[93.836,194.483],[56.285,260.392],[50.768,265.909],[59.126,271.426],[93.836,205.517],[141.517,248],[189.517,200],[189.514,199.724],[189.517,199.724],[201.379,187.862],[213.241,199.724],[213.245,199.724],[213.241,200],[261.241,248],[308.922,205.517],[340.341,271.426],[348.699,265.909]],"c":true}]},{"i":{"x":0.667,"y":1},"o":{"x":0.333,"y":0},"t":10,"s":[{"i":[[3.047,0],[0,0],[24.601,0],[6.991,-17.874],[5.801,0],[4.039,-3.568],[20.321,0],[2.745,-23.878],[0,0],[0,-3.047],[-3.047,0],[0,0],[-24.602,0],[0,26.467],[0.001,0.092],[0,0],[-6.541,0],[0,-6.541],[0,0],[0,-0.092],[-26.467,0],[-2.745,23.878],[0,0],[0,3.047]],"o":[[0,0],[-2.745,-23.878],[-20.321,0],[-4.039,-3.568],[-5.8,0],[-6.991,-17.874],[-24.602,0],[0,0],[-3.047,0],[0,3.047],[0,0],[2.745,23.878],[26.467,0],[0,-0.092],[0,0],[0,-6.541],[6.541,0],[0,0],[-0.001,0.092],[0,26.467],[24.601,0],[0,0],[3.047,0],[0,-3.047]],"v":[[343.448,194.483],[308.922,194.483],[261.241,152],[216.519,182.568],[201.379,176.828],[186.24,182.568],[141.517,152],[93.836,194.483],[56.552,194.483],[51.034,200],[56.552,205.517],[93.836,205.517],[141.517,248],[189.517,200],[189.514,199.724],[189.517,199.724],[201.379,187.862],[213.241,199.724],[213.245,199.724],[213.241,200],[261.241,248],[308.922,205.517],[343.448,205.517],[348.966,200]],"c":true}]},{"i":{"x":0.667,"y":1},"o":{"x":0.333,"y":0},"t":45,"s":[{"i":[[3.047,0],[0,0],[24.601,0],[6.991,-17.874],[5.801,0],[4.039,-3.568],[20.321,0],[2.745,-23.878],[0,0],[0,-3.047],[-3.047,0],[0,0],[-24.602,0],[0,26.467],[0.001,0.092],[0,0],[-6.541,0],[0,-6.541],[0,0],[0,-0.092],[-26.467,0],[-2.745,23.878],[0,0],[0,3.047]],"o":[[0,0],[-2.745,-23.878],[-20.321,0],[-4.039,-3.568],[-5.8,0],[-6.991,-17.874],[-24.602,0],[0,0],[-3.047,0],[0,3.047],[0,0],[2.745,23.878],[26.467,0],[0,-0.092],[0,0],[0,-6.541],[6.541,0],[0,0],[-0.001,0.092],[0,26.467],[24.601,0],[0,0],[3.047,0],[0,-3.047]],"v":[[343.448,194.483],[308.922,194.483],[261.241,152],[216.519,182.568],[201.379,176.828],[186.24,182.568],[141.517,152],[93.836,194.483],[56.552,194.483],[51.034,200],[56.552,205.517],[93.836,205.517],[141.517,248],[189.517,200],[189.514,199.724],[189.517,199.724],[201.379,187.862],[213.241,199.724],[213.245,199.724],[213.241,200],[261.241,248],[308.922,205.517],[343.448,205.517],[348.966,200]],"c":true}]},{"t":50.0000020365418,"s":[{"i":[[3.047,0],[0,0],[24.601,0],[6.991,-17.874],[5.801,0],[4.039,-3.568],[20.321,0],[2.745,-23.878],[0,0],[0,-3.047],[-3.047,0],[0,0],[-24.602,0],[0,26.467],[0.001,0.092],[0,0],[-6.541,0],[0,-6.541],[0,0],[0,-0.092],[-26.467,0],[-2.745,23.878],[0,0],[0,3.047]],"o":[[0,0],[-2.745,-23.878],[-20.321,0],[-4.039,-3.568],[-5.8,0],[-6.991,-17.874],[-24.602,0],[0,0],[-3.047,0],[0,3.047],[0,0],[2.745,23.878],[26.467,0],[0,-0.092],[0,0],[0,-6.541],[6.541,0],[0,0],[-0.001,0.092],[0,26.467],[24.601,0],[0,0],[3.047,0],[0,-3.047]],"v":[[343.182,260.392],[308.922,194.483],[261.241,152],[216.519,182.568],[201.379,176.828],[186.24,182.568],[141.517,152],[93.836,194.483],[56.285,260.392],[50.768,265.909],[59.126,271.426],[93.836,205.517],[141.517,248],[189.517,200],[189.514,199.724],[189.517,199.724],[201.379,187.862],[213.241,199.724],[213.245,199.724],[213.241,200],[261.241,248],[308.922,205.517],[340.341,271.426],[348.699,265.909]],"c":true}]}],"ix":1},"o":{"a":0,"k":100,"ix":3},"x":{"a":0,"k":0,"ix":4},"nm":"Mask 1"},{"inv":false,"mode":"s","pt":{"a":0,"k":{"i":[[20.383,0],[0,20.383],[-20.383,0],[0,-20.383]],"o":[[-20.383,0],[0,-20.383],[20.383,0],[0,20.383]],"v":[[141.517,236.965],[104.552,200],[141.517,163.035],[178.483,200]],"c":true},"ix":1},"o":{"a":0,"k":100,"ix":3},"x":{"a":0,"k":0,"ix":4},"nm":"Mask 2"},{"inv":false,"mode":"s","pt":{"a":0,"k":{"i":[[20.383,0],[0,20.383],[-20.383,0],[0,-20.383]],"o":[[-20.383,0],[0,-20.383],[20.383,0],[0,20.383]],"v":[[261.241,236.965],[224.276,200],[261.241,163.035],[298.207,200]],"c":true},"ix":1},"o":{"a":0,"k":100,"ix":3},"x":{"a":0,"k":0,"ix":4},"nm":"Mask 3"}],"sw":400,"sh":400,"sc":"#442f01","ip":0,"op":61.0000024845809,"st":0,"bm":0},{"ddd":0,"ind":6,"ty":0,"nm":"boca","parent":9,"refId":"comp_0","sr":1,"ks":{"o":{"a":0,"k":100,"ix":11},"r":{"a":0,"k":0,"ix":10},"p":{"a":0,"k":[-32.479,49.814,0],"ix":2},"a":{"a":0,"k":[200,200,0],"ix":1},"s":{"a":0,"k":[100,100,100],"ix":6}},"ao":0,"hasMask":true,"masksProperties":[{"inv":false,"mode":"a","pt":{"a":0,"k":{"i":[[13.093,-7.249],[1.11,-0.957],[0,0]],"o":[[-13.093,7.249],[44.61,14.043],[0,0]],"v":[[283.873,228.734],[253.171,241.44],[305.377,211.001]],"c":true},"ix":1},"o":{"a":0,"k":100,"ix":3},"x":{"a":0,"k":0,"ix":4},"nm":"Mask 1"}],"w":400,"h":400,"ip":0,"op":600.000024438501,"st":0,"bm":0},{"ddd":0,"ind":7,"ty":4,"nm":"EYE-R","parent":9,"sr":1,"ks":{"o":{"a":0,"k":100,"ix":11},"r":{"a":0,"k":180,"ix":10},"p":{"a":0,"k":[55.301,-4.703,0],"ix":2},"a":{"a":0,"k":[-44.028,28.571,0],"ix":1},"s":{"a":0,"k":[-220,-220,100],"ix":6}},"ao":0,"shapes":[{"ty":"gr","it":[{"d":1,"ty":"el","s":{"a":0,"k":[28.792,30.195],"ix":2},"p":{"a":0,"k":[0,0],"ix":3},"nm":"Ellipse Path 1","mn":"ADBE Vector Shape - Ellipse","hd":false},{"ty":"fl","c":{"a":0,"k":[0.266666666667,0.18431372549,0.003921568627,1],"ix":4},"o":{"a":0,"k":100,"ix":5},"r":1,"bm":0,"nm":"Fill 1","mn":"ADBE Vector Graphic - Fill","hd":false},{"ty":"tr","p":{"a":0,"k":[-44.015,28.347],"ix":2},"a":{"a":0,"k":[0,0],"ix":1},"s":{"a":0,"k":[43.396,49.427],"ix":3},"r":{"a":0,"k":0,"ix":6},"o":{"a":0,"k":100,"ix":7},"sk":{"a":0,"k":0,"ix":4},"sa":{"a":0,"k":0,"ix":5},"nm":"Transform"}],"nm":"Ellipse 2","np":3,"cix":2,"bm":0,"ix":1,"mn":"ADBE Vector Group","hd":false}],"ip":0,"op":61.0000024845809,"st":0,"bm":0},{"ddd":0,"ind":8,"ty":4,"nm":"EYE-L","parent":9,"sr":1,"ks":{"o":{"a":0,"k":100,"ix":11},"r":{"a":0,"k":180,"ix":10},"p":{"a":0,"k":[-52.699,-4.703,0],"ix":2},"a":{"a":0,"k":[-44.028,28.571,0],"ix":1},"s":{"a":0,"k":[-220,-220,100],"ix":6}},"ao":0,"shapes":[{"ty":"gr","it":[{"d":1,"ty":"el","s":{"a":0,"k":[28.792,30.195],"ix":2},"p":{"a":0,"k":[0,0],"ix":3},"nm":"Ellipse Path 1","mn":"ADBE Vector Shape - Ellipse","hd":false},{"ty":"fl","c":{"a":0,"k":[0.266666666667,0.18431372549,0.003921568627,1],"ix":4},"o":{"a":0,"k":100,"ix":5},"r":1,"bm":0,"nm":"Fill 1","mn":"ADBE Vector Graphic - Fill","hd":false},{"ty":"tr","p":{"a":0,"k":[-44.015,28.347],"ix":2},"a":{"a":0,"k":[0,0],"ix":1},"s":{"a":0,"k":[43.396,49.427],"ix":3},"r":{"a":0,"k":0,"ix":6},"o":{"a":0,"k":100,"ix":7},"sk":{"a":0,"k":0,"ix":4},"sa":{"a":0,"k":0,"ix":5},"nm":"Transform"}],"nm":"Ellipse 2","np":3,"cix":2,"bm":0,"ix":1,"mn":"ADBE Vector Group","hd":false}],"ip":0,"op":61.0000024845809,"st":0,"bm":0},{"ddd":0,"ind":9,"ty":4,"nm":"HEAD","sr":1,"ks":{"o":{"a":0,"k":100,"ix":11},"r":{"a":0,"k":0,"ix":10},"p":{"a":0,"k":[200.699,325.203,0],"ix":2},"a":{"a":0,"k":[2,144,0],"ix":1},"s":{"a":0,"k":[100,100,100],"ix":6}},"ao":0,"shapes":[{"ty":"gr","it":[{"d":1,"ty":"el","s":{"a":0,"k":[248.195,248.195],"ix":2},"p":{"a":0,"k":[0,0],"ix":3},"nm":"Ellipse Path 1","mn":"ADBE Vector Shape - Ellipse","hd":false},{"ty":"st","c":{"a":0,"k":[0.267723651961,0.185453931023,0.002169511832,1],"ix":3},"o":{"a":0,"k":100,"ix":4},"w":{"a":0,"k":6,"ix":5},"lc":1,"lj":1,"ml":4,"bm":0,"nm":"Stroke 1","mn":"ADBE Vector Graphic - Stroke","hd":false},{"ty":"gf","o":{"a":0,"k":100,"ix":10},"r":1,"bm":0,"g":{"p":3,"k":{"a":0,"k":[0,1,1,1,0.199,1,0.86,0.5,0.398,1,0.721,0],"ix":9}},"s":{"a":0,"k":[-87.371,88.162],"ix":5},"e":{"a":0,"k":[87.32,-88.171],"ix":6},"t":2,"h":{"a":0,"k":0,"ix":7},"a":{"a":0,"k":0,"ix":8},"nm":"Gradient Fill 1","mn":"ADBE Vector Graphic - G-Fill","hd":false},{"ty":"tr","p":{"a":0,"k":[1.301,18.797],"ix":2},"a":{"a":0,"k":[0,0],"ix":1},"s":{"a":0,"k":[100,100],"ix":3},"r":{"a":0,"k":0,"ix":6},"o":{"a":0,"k":100,"ix":7},"sk":{"a":0,"k":0,"ix":4},"sa":{"a":0,"k":0,"ix":5},"nm":"Transform"}],"nm":"Ellipse 1","np":3,"cix":2,"bm":0,"ix":1,"mn":"ADBE Vector Group","hd":false}],"ip":0,"op":61.0000024845809,"st":0,"bm":0}],"markers":[]}